gym_vectorvelocity/__init__.py
gym_vectorvelocity/env.py
gym_vectorvelocity/utils.py
gym_vectorvelocity/game/__init__.py
gym_vectorvelocity/game/asset_manager.py
gym_vectorvelocity/game/coin.py
gym_vectorvelocity/game/game.py
gym_vectorvelocity/game/level_area.py
gym_vectorvelocity/game/obstacle.py
gym_vectorvelocity/game/player.py
gym_vectorvelocity/game/settings.py
gym_vectorvelocity/game/spawn_manager.py
gym_vectorvelocity/game/ui.py
gym_vectorvelocity/game/assets/bg.jpg
gym_vectorvelocity/game/assets/ship.png
gym_vectorvelocity/game/assets/obstacles/obstacle_1.png
gym_vectorvelocity/game/assets/obstacles/obstacle_2.png
gym_vectorvelocity/game/assets/obstacles/obstacle_3.png
gym_vectorvelocity/game/assets/obstacles/obstacle_4.png
gym_vectorvelocity/game/assets/obstacles/obstacle_5.png
gym_vectorvelocity/game/assets/sounds/bgmusic.wav
vector_velocity_gym-0.1.2.dist-info/LICENSE
vector_velocity_gym-0.1.2.dist-info/METADATA
vector_velocity_gym-0.1.2.dist-info/WHEEL
vector_velocity_gym-0.1.2.dist-info/top_level.txt
vector_velocity_gym-0.1.2.dist-info/RECORD
