Metadata-Version: 2.1
Name: vector-velocity-gym
Version: 0.1.2
Summary: A space-themed OpenAI Gym environment for reinforcement learning
Home-page: https://github.com/MrChriwo/VectorVelocity
Author: MrChriwo & Stevenschneider
Maintainer: MrChriwo
License: GPL-3.0
License-File: LICENSE
Requires-Dist: gymnasium
Requires-Dist: pygame
Requires-Dist: numpy
